CONTRIBUTING.md
dff/__init__.py
dff/config/README.md
dff/config/superset_dashboard/charts/Current_topic_slot_bar_chart_4.yaml
dff/config/superset_dashboard/charts/Current_topic_time_series_bar_chart_2.yaml
dff/config/superset_dashboard/charts/Flow_visit_ratio_monitor_13.yaml
dff/config/superset_dashboard/charts/Node_Visits_7.yaml
dff/config/superset_dashboard/charts/Node_counts_3.yaml
dff/config/superset_dashboard/charts/Node_visit_ratio_monitor_8.yaml
dff/config/superset_dashboard/charts/Node_visits_ratio_6.yaml
dff/config/superset_dashboard/charts/Node_visits_sunburst_5.yaml
dff/config/superset_dashboard/charts/Rating_slot_line_chart_1.yaml
dff/config/superset_dashboard/charts/Requests_17.yaml
dff/config/superset_dashboard/charts/Responses_16.yaml
dff/config/superset_dashboard/charts/Service_load_users_9.yaml
dff/config/superset_dashboard/charts/Table_14.yaml
dff/config/superset_dashboard/charts/Terminal_labels_15.yaml
dff/config/superset_dashboard/charts/Transition_counts_12.yaml
dff/config/superset_dashboard/charts/Transition_layout_10.yaml
dff/config/superset_dashboard/charts/Transition_ratio_chord_11.yaml
dff/config/superset_dashboard/dashboards/DFF_statistics_dashboard_1.yaml
dff/config/superset_dashboard/databases/dff_database.yaml
dff/config/superset_dashboard/datasets/dff_database/dff_final_nodes.yaml
dff/config/superset_dashboard/datasets/dff_database/dff_node_stats.yaml
dff/config/superset_dashboard/datasets/dff_database/dff_stats.yaml
dff/config/superset_dashboard/metadata.yaml
dff/context_storages/__init__.py
dff/context_storages/database.py
dff/context_storages/json.py
dff/context_storages/mongo.py
dff/context_storages/pickle.py
dff/context_storages/protocol.py
dff/context_storages/protocols.json
dff/context_storages/redis.py
dff/context_storages/shelve.py
dff/context_storages/sql.py
dff/context_storages/ydb.py
dff/messengers/__init__.py
dff/messengers/common/__init__.py
dff/messengers/common/interface.py
dff/messengers/common/types.py
dff-0.7.2.dist-info/LICENSE
dff-0.7.2.dist-info/METADATA
dff-0.7.2.dist-info/WHEEL
dff-0.7.2.dist-info/entry_points.txt
dff-0.7.2.dist-info/RECORD
